MANIFEST.in
README.rst
setup.py
django_quickedit_ng.egg-info/PKG-INFO
django_quickedit_ng.egg-info/SOURCES.txt
django_quickedit_ng.egg-info/dependency_links.txt
django_quickedit_ng.egg-info/top_level.txt
quickedit/__init__.py
quickedit/admin.py
quickedit/templates/quickedit/change_list.html
quickedit/templates/quickedit/change_list_results.html
quickedit/templatetags/__init__.py
quickedit/templatetags/quickedit.py